shirabe/__init__.py
shirabe/__main__.py
shirabe/cli.py
shirabe/deps.py
shirabe/venv.py
shirabe-0.1.0.dist-info/LICENSE
shirabe-0.1.0.dist-info/METADATA
shirabe-0.1.0.dist-info/WHEEL
shirabe-0.1.0.dist-info/entry_points.txt
shirabe-0.1.0.dist-info/top_level.txt
shirabe-0.1.0.dist-info/RECORD
